{"id":250000874104,"nomeUrna":"GISELA AMBROSIO","numero":23232,"idCandidatoSuperior":0,"nomeCompleto":"GISELA MARCIA DE FREITAS AMBROSIO","descricaoSexo":"FEM.","dataDeNascimento":"1963-09-14","tituloEleitor":"020483350108","cpf":"07178052805","descricaoEstadoCivil":"Casado(a)","descricaoCorRaca":"BRANCA","descricaoSituacao":"Aguardando julgamento","nacionalidade":"Brasileira nata","grauInstrucao":"Superior completo","ocupacao":"Farmacêutico","gastoCampanha1T":66966.99,"gastoCampanha2T":0,"sgUfNascimento":"SP","nomeMunicipioNascimento":"GUARÁ","localCandidatura":"FRANCA","ufCandidatura":"64254","ufSuperiorCandidatura":"SP","dataUltimaAtualizacao":"2020-09-25","fotoUrl":"http://divulgacandcontas.tse.jus.br/candidaturas/oficial/2020/SP/64254/426/candidatos/288509/foto.jpg","fotoDataUltimaAtualizacao":null,"descricaoTotalizacao":"Concorrendo","nomeColigacao":"CIDADANIA","composicaoColigacao":"**","numeroProcessoDrap":"06000799720206260291","numeroProcessoDrapEncrypt":"185e229217a581757a9771746e685d0f367a81717834983a6d976365c580b39ba51fc66567b5510d","numeroProcesso":"06000825220206260291","numeroProcessoEncrypt":"8239ccca1715975381e225a0c2cc3878367a81717834983a6d976365c580b39ba51fc66567b5510d","numeroProcessoPrestContas":null,"numeroProcessoPrestContasEncrypt":null,"numeroProtocolo":null,"cargo":{"codigo":13,"sigla":null,"nome":"Vereador","codSuperior":0,"titular":true,"contagem":0},"bens":[{"ordem":6,"descricao":"QUOTAS DE CAPITAL DA FIRMA LUMAR COMERCIO DE PRODUTOS FARMACEUTICOS LTDA","descricaoDeTipoDeBem":"Quotas ou quinhões de capital","valor":44000,"dataUltimaAtualizacao":"2020-09-23"},{"ordem":7,"descricao":"CONTA POUPANÇA NO BANCO SANTANDER","descricaoDeTipoDeBem":"Caderneta de poupança","valor":6306.44,"dataUltimaAtualizacao":"2020-09-23"},{"ordem":4,"descricao":"AUTOMOVEL VW FUSCA 1300 ANO 1974 ","descricaoDeTipoDeBem":"Veículo automotor terrestre: caminhão, automóvel, moto, etc.","valor":6000,"dataUltimaAtualizacao":"2020-09-23"},{"ordem":1,"descricao":"1/4 DE UM IMOVEL EM FRANCA SP, PREDIO EM FRENTE A RUA SIMÃO CALEIRO, 1626","descricaoDeTipoDeBem":"Casa","valor":38840.27,"dataUltimaAtualizacao":"2020-09-23"},{"ordem":9,"descricao":"DINHEIRO E HAVERES","descricaoDeTipoDeBem":"OUTROS BENS E DIREITOS","valor":26750,"dataUltimaAtualizacao":"2020-09-23"},{"ordem":2,"descricao":"1/4 DE IMOVEL EM FRANCA SP, SENDO UM PREDIO COMERCIAL E EDICULA EDIFICIO MARIA DO ROSARIO DE FRENTE A AV PRESIDENTE VARGAS 783, UNIDADE 1 ","descricaoDeTipoDeBem":"Outros bens imóveis","valor":54570.67,"dataUltimaAtualizacao":"2020-09-23"},{"ordem":3,"descricao":"APARTAMENTO NA AVENIDA PRESIDENTE VARGAS, 779","descricaoDeTipoDeBem":"Apartamento","valor":83444.32,"dataUltimaAtualizacao":"2020-09-23"},{"ordem":5,"descricao":"CHEVROLET CRUZE LT BRANCO ANO 2012/2012","descricaoDeTipoDeBem":"Veículo automotor terrestre: caminhão, automóvel, moto, etc.","valor":35000,"dataUltimaAtualizacao":"2020-09-23"},{"ordem":10,"descricao":"PREMIOS ACUMULADOS","descricaoDeTipoDeBem":"VGBL - Vida Gerador de Benefício Livre","valor":31235.9,"dataUltimaAtualizacao":"2020-09-23"},{"ordem":8,"descricao":"APLICAÇÃO RENDA FIXA BANCO SANTANDER","descricaoDeTipoDeBem":"Aplicação de renda fixa (CDB, RDB e outros)","valor":6777.44,"dataUltimaAtualizacao":"2020-09-23"}],"totalDeBens":332925.04,"vices":null,"partido":{"numero":23,"sigla":"CIDADANIA","nome":"Cidadania"},"eleicao":{"id":2030402020,"siglaUF":null,"localidadeSgUe":null,"ano":2020,"codigo":null,"nomeEleicao":null,"tipoEleicao":null,"turno":null,"tipoAbrangencia":null,"dataEleicao":null,"codSituacaoEleicao":null,"descricaoSituacaoEleicao":null,"descricaoEleicao":"2020"},"emails":["GISAMBROSIO@HOTMAIL.COM"],"sites":["https://instagram.com/giselambrosio20?igshid=1l9klbywr9kya"],"arquivos":[{"idArquivo":250007466675,"nome":"12_1600168437288.pdf","url":"candidaturas/oficial/2020/SP/64254/426/candidatos/288509/","tipo":"pdf","codTipo":"12","fullFilePath":null,"fileInputStream":null,"fileByteArray":null},{"idArquivo":250007466674,"nome":"14_1600168436305.pdf","url":"candidaturas/oficial/2020/SP/64254/426/candidatos/288509/","tipo":"pdf","codTipo":"14","fullFilePath":null,"fileInputStream":null,"fileByteArray":null},{"idArquivo":250007466672,"nome":"13_1600168435610.pdf","url":"candidaturas/oficial/2020/SP/64254/426/candidatos/288509/","tipo":"pdf","codTipo":"13","fullFilePath":null,"fileInputStream":null,"fileByteArray":null},{"idArquivo":250007466671,"nome":"11_1600168435127.pdf","url":"candidaturas/oficial/2020/SP/64254/426/candidatos/288509/","tipo":"pdf","codTipo":"11","fullFilePath":null,"fileInputStream":null,"fileByteArray":null}],"eleicoesAnteriores":[{"nrAno":2020,"id":"250000874104","nomeUrna":"GISELA AMBROSIO","nomeCandidato":"GISELA MARCIA DE FREITAS AMBROSIO","idEleicao":"2030402020","sgUe":"64254","local":"FRANCA","cargo":"Vereador","partido":"CIDADANIA","situacaoTotalizacao":"Concorrendo","txLink":"http://divulgacandcontas.tse.jus.br/divulga/#/candidato/2020/2030402020/64254/250000874104"}],"substituto":null,"motivos":null,"codigoSituacaoCandidato":8,"descricaoSituacaoCandidato":"CADASTRADO","st_SUBSTITUIDO":false,"descricaoNaturalidade":"SP-GUARÁ","st_DIVULGA_BENS":true,"st_MOTIVO_COMPRA_VOTO":false,"st_DIVULGA_ARQUIVOS":false,"st_MOTIVO_IND_PARTIDO":false,"st_MOTIVO_GASTO_ILICITO":false,"st_MOTIVO_FICHA_LIMPA":false,"ds_MOTIVO_OUTROS":null,"st_MOTIVO_CONDUTA_VEDADA":false,"st_MOTIVO_AUSENCIA_REQUISITO":false,"cnpjcampanha":"38784150000106","gastoCampanha":0,"st_MOTIVO_ABUSO_PODER":false,"st_DIVULGA":true,"st_REELEICAO":false}